{
	"data": [{
			"id": "1",
			"imagen": "venerdì",
			"contenido": ""
		},
		{
			"id": "2",
			"imagen": "sabato",
			"contenido": ""
		},
		{
			"id": "3",
			"imagen": "domenica",
			"contenido": ""
		},
		{
			"id": "4",
			"imagen": "lunedì",
			"contenido": ""
		},
		{
			"id": "5",
			"imagen": "martedì",
			"contenido": ""
		},
		{
			"id": "6",
			"imagen": "mercoledì",
			"contenido": ""
		},
		{
			"id": "7",
			"imagen": "giovedì",
			"contenido": ""
		},
		{
			"id": "8",
			"imagen": "venerdì",
			"contenido": ""
		},
		{
			"id": "9",
			"imagen": "sabato",
			"contenido": ""
		},
		{
			"id": "10",
			"imagen": "domenica",
			"contenido": ""
		},
		{
			"id": "11",
			"imagen": "lunedì",
			"contenido": ""
		},
		{
			"id": "12",
			"imagen": "martedì",
			"contenido": ""
		},
		{
			"id": "13",
			"imagen": "mercoledì",
			"contenido": ""
		},
		{
			"id": "14",
			"imagen": "giovedì",
			"contenido": ""
		},
		{
			"id": "15",
			"imagen": "venerdì",
			"contenido": ""
		},
		{
			"id": "16",
			"imagen": "sabato",
			"contenido": ""
		},
		{
			"id": "17",
			"imagen": "domenica",
			"contenido": ""
		},
		{
			"id": "18",
			"imagen": "lunedì",
			"contenido": ""
		},
		{
			"id": "19",
			"imagen": "martedì",
			"contenido": ""
		},
		{
			"id": "20",
			"imagen": "mercoledì",
			"contenido": ""
		},
		{
			"id": "21",
			"imagen": "giovedì",
			"contenido": ""
		},
		{
			"id": "22",
			"imagen": "venerdì",
			"contenido": ""
		},
		{
			"id": "23",
			"imagen": "sabato",
			"contenido": ""
		},
		{
			"id": "24",
			"imagen": "domenica",
			"contenido": ""
		},
		{
			"id": "25",
			"imagen": "lunedì",
			"contenido": ""
		},
		{
			"id": "26",
			"imagen": "martedì",
			"contenido": ""
		},
		{
			"id": "27",
			"imagen": "mercoledì",
			"contenido": ""
		},
		{
			"id": "28",
			"imagen": "giovedì",
			"contenido": ""
		},
		{
			"id": "29",
			"imagen": "venerdì",
			"contenido": ""
		},
		{
			"id": "30",
			"imagen": "sabato",
			"contenido": ""
		},
		{
			"id": "31",
			"imagen": "domenica",
			"contenido": ""
		}
	]
}
